llm_hub_sdk/__init__.py
llm_hub_sdk/anthropic.py
llm_hub_sdk/core.py
llm_hub_sdk/exceptions.py
llm_hub_sdk/gemini.py
llm_hub_sdk/openai.py
llm_hub_sdk-0.0.4.dist-info/licenses/LICENSE.md
llm_hub_sdk-0.0.4.dist-info/METADATA
llm_hub_sdk-0.0.4.dist-info/WHEEL
llm_hub_sdk-0.0.4.dist-info/top_level.txt
llm_hub_sdk-0.0.4.dist-info/RECORD
