Metadata-Version: 2.4
Name: llm-hub-sdk
Version: 0.0.4
Summary: This Python SDK that provides convenient clients for interacting with the LLM-HUB – a centralized backend service
Author: NTV360
License: LICENSE
Keywords: llm,hub,sdk,api,chat,generative-ai
Classifier: Programming Language :: Python :: 3
Classifier: Programming Language :: Python :: 3.9
Classifier: Programming Language :: Python :: 3.10
Classifier: Programming Language :: Python :: 3.11
Classifier: Programming Language :: Python :: 3.12
Classifier: Operating System :: OS Independent
Requires-Python: >=3.9
License-File: LICENSE.md
Requires-Dist: requests>=2.32.3
Provides-Extra: dev
Requires-Dist: pytest>=7.0; extra == "dev"
Requires-Dist: ruff; extra == "dev"
Requires-Dist: black; extra == "dev"
Requires-Dist: mypy; extra == "dev"
Requires-Dist: build; extra == "dev"
Requires-Dist: twine; extra == "dev"
Requires-Dist: python-dotenv; extra == "dev"
Requires-Dist: docutils!=0.21.post1,>=0.21; extra == "dev"
Dynamic: license-file
